ghwnvci/__init__.py
ghwnvci/conman.py
ghwnvci/get_branch_config.py
ghwnvci/main.py
ghwnvci/nvci_asbtest.py
ghwnvci/nvci_migrate.py
ghwnvci/nvci_snapshot.py
ghwnvci/py.typed
ghwnvci/rules_cl.py
ghwnvci/set_project_team.py
ghwnvci/site_path.py
ghwnvci/wm_util.py
ghwnvci/workspace.py
ghwnvci/workspace_utils.py
ghwnvci/xform.py
ghwnvci/ytt_parse.py
ghwnvci-1.0.16.dist-info/METADATA
ghwnvci-1.0.16.dist-info/WHEEL
ghwnvci-1.0.16.dist-info/entry_points.txt
ghwnvci-1.0.16.dist-info/RECORD
